[{"institution":"Chandigarh University","name":"Prasanna Kumar","course":"CSE","skills":[{"name":"competitive programming","level":3,"subdomains":[{"name":"codechef","level":2071},{"name":"codeforces","level":1760},{"name":"data structures and agorithms","level":3}]},{"name":"object oriented programming","level":3,"subdomains":[{"name":"c++","level":3},{"name":"java","level":1},{"name":"python","level":2}]},{"name":"web development","level":2,"subdomains":[{"name":"css","level":2},{"name":"html","level":2},{"name":"javascript","level":1}]}]},{"institution":"Chandigarh University","name":"Amit Kumar","course":"CSE","skills":[{"name":"competitive programming","level":3,"subdomains":[{"name":"codechef","level":2001},{"name":"codeforces","level":1570},{"name":"data structures and agorithms","level":3}]},{"name":"object oriented programming","level":3,"subdomains":[{"name":"c++","level":3},{"name":"java","level":1},{"name":"python","level":3}]},{"name":"web development","level":3,"subdomains":[{"name":"css","level":3},{"name":"html","level":3},{"name":"javascript","level":2},{"name":"nodejs","level":2}]}]},{"institution":"Punjab University","name":"Anuj Goyal","course":"ECE","skills":[{"name":"Machine Learning","level":3,"subdomains":[{"name":"nlp","level":2},{"name":"python","level":3},{"name":"r","level":2}]},{"name":"competitive programming","level":2,"subdomains":[{"name":"codechef","level":1649},{"name":"codeforces","level":1350},{"name":"data structures and agorithms","level":2}]},{"name":"web development","level":4,"subdomains":[{"name":"css","level":4},{"name":"html","level":4},{"name":"javascript","level":4},{"name":"nodejs","level":3}]}]},{"institution":"IIT Rurkee","name":"Rishab Verma","course":"ECE","skills":[{"name":"competitive programming","level":4,"subdomains":[{"name":"codechef","level":2260},{"name":"codeforces","level":2151},{"name":"data structures and agorithms","level":4},{"name":"hackerearth","level":2021}]},{"name":"machine learning","level":3,"subdomains":[{"name":"deep learning","level":3},{"name":"python","level":3},{"name":"r","level":3}]},{"name":"object oriented programming","level":3,"subdomains":[{"name":"c#","level":3},{"name":"c++","level":2},{"name":"java","level":2},{"name":"python","level":4}]},{"name":"web development","level":4,"subdomains":[{"name":"css","level":4},{"name":"html","level":4},{"name":"javascript","level":4},{"name":"mern stack","level":4},{"name":"nodejs","level":4},{"name":"reactjs","level":4},{"name":"vuejs","level":4}]}]},{"institution":"DTU","name":"Jatin Khandual","course":"CSE","skills":[{"name":"competitive programming","level":4,"subdomains":[{"name":"codechef","level":2241},{"name":"codeforces","level":1700},{"name":"data structures and agorithms","level":4}]},{"name":"mathematics","level":4},{"name":"object oriented programming","level":3,"subdomains":[{"name":"c++","level":3},{"name":"java","level":2},{"name":"python","level":2}]},{"name":"web development","level":2,"subdomains":[{"name":"css","level":2},{"name":"html","level":2},{"name":"javascript","level":2}]}]}]